{
  "updated_at": "2026-03-06T00:00:00Z",
  "ciffc": {
    "active_fires": 0,
    "ha_burned_ytd": 0,
    "preparedness_level": 1,
    "interprovincial_requests": 0,
    "source": "https://ciffc.net",
    "note": "Off-season. National fire statistics will be updated when the 2026 fire season begins."
  },
  "provinces": [
    {
      "id": "bc",
      "name": "BC",
      "active": 0,
      "ha": 0,
      "level": 1
    },
    {
      "id": "ab",
      "name": "AB",
      "active": 0,
      "ha": 0,
      "level": 1
    },
    {
      "id": "sk",
      "name": "SK",
      "active": 0,
      "ha": 0,
      "level": 1
    },
    {
      "id": "mb",
      "name": "MB",
      "active": 0,
      "ha": 0,
      "level": 1
    },
    {
      "id": "on",
      "name": "ON",
      "active": 0,
      "ha": 0,
      "level": 1
    },
    {
      "id": "qc",
      "name": "QC",
      "active": 0,
      "ha": 0,
      "level": 1
    },
    {
      "id": "nb",
      "name": "NB",
      "active": 0,
      "ha": 0,
      "level": 1
    },
    {
      "id": "ns",
      "name": "NS",
      "active": 0,
      "ha": 0,
      "level": 1
    },
    {
      "id": "nt",
      "name": "NT",
      "active": 0,
      "ha": 0,
      "level": 1
    },
    {
      "id": "yt",
      "name": "YT",
      "active": 0,
      "ha": 0,
      "level": 1
    }
  ],
  "news": [
    {
      "title": "Out-of-control wildfire forces evacuation in B.C.'s Fraser Canyon",
      "url": "https://globalnews.ca/news/11953588/wildfire-evacuation-fraser-valley-bc/",
      "source": "Global News Wildfire",
      "published": "2026-07-05",
      "description": "Residents of North Bend, B.C. are being ordered to evacuate as an out of control wildfire grows in the Fraser Canyon. Nearby Boston Bar is also under an evacuation alert.",
      "image": "https://globalnews.ca/wp-content/uploads/2026/07/Boston-Bar-wildfire-e1783263304408.jpg?quality=65&strip=all"
    },
    {
      "title": "Manitoba town residents set to return home after wildfire forced evacuation",
      "url": "https://globalnews.ca/news/11950289/manitoba-lynn-lake-return-home-after-wildfire-evacuation/",
      "source": "Global News Wildfire",
      "published": "2026-07-02",
      "description": "A social media post by the town of Lynn Lake says that the nearby blaze remains active, and that crews continue to suppress remaining hot spots.",
      "image": "https://globalnews.ca/wp-content/uploads/2026/07/513e47cf161bffa0d0fb544af541353dd8965a7a6b5e015653ddeb903587f902.jpg?quality=65&strip=all"
    },
    {
      "title": "Wildfire forces evacuation of remote Northwest Territories village",
      "url": "https://globalnews.ca/news/11942614/northwest-territories-village-evacuation-wildfire/",
      "source": "Global News Wildfire",
      "published": "2026-06-29"
    }
  ],
  "last_news_update": "2026-07-08T04:00:51.683Z"
}